calculadora_simples/__init__.py
calculadora_simples/calculadora_simples.py
calculador_simples-0.0.1.dist-info/METADATA
calculador_simples-0.0.1.dist-info/WHEEL
calculador_simples-0.0.1.dist-info/top_level.txt
calculador_simples-0.0.1.dist-info/RECORD
