Metadata-Version: 2.1
Name: calculador-simples
Version: 0.0.1
Summary: Calculadora simples feita em Python
Home-page: https://github.com/gabrielferrazs/calculadora_simples
Author: gabriel_rodrigues_ferraz_da_silva
Author-email: gabrielcma_@hotmail.com
License: UNKNOWN
Platform: UNKNOWN
Requires-Python: >=3.6
Requires-Dist: numpy
